Metadata-Version: 2.1
Name: dffml-operations-image
Version: 0.1.0.post0
Summary: DFFML operations image
Home-page: https://github.com/sakshamarora1/dffml-operations-image
Author: Saksham Arora
Author-email: sakshamarora1001@gmail.com
Maintainer: Saksham Arora
Maintainer-email: sakshamarora1001@gmail.com
License: MIT
Keywords: dffml
Platform: UNKNOWN
Classifier: Development Status :: 3 - Alpha
Classifier: Intended Audience :: Developers
Classifier: License :: OSI Approved :: MIT License
Classifier: Natural Language :: English
Classifier: Operating System :: OS Independent
Classifier: Programming Language :: Python :: 3 :: Only
Classifier: Programming Language :: Python :: 3.7
Classifier: Programming Language :: Python :: Implementation :: CPython
Classifier: Programming Language :: Python :: Implementation :: PyPy
License-File: LICENSE
Requires-Dist: dffml (>=0.4.0)
Requires-Dist: opencv-python (>=4.2.0.34)
Requires-Dist: numpy (>=1.19.2)
Requires-Dist: mahotas (>=1.4.9)
